{
  "NYC-TYO-2026-09-10": {
    "last_checked": "2026-07-01T23:08:48.408763+00:00",
    "last_price": 996,
    "under_target": false
  },
  "KUL-CAN-2026-09-24": {
    "last_checked": "2026-07-02T11:59:42.326001+00:00",
    "last_price": 1139,
    "under_target": true,
    "consecutive_failures": 0,
    "failure_alert_sent": false,
    "price_log": [
      {
        "date": "2026-07-02T11:59:42.326001+00:00",
        "price": 1139
      }
    ]
  },
  "KUL-BTH-2026-09-24": {
    "last_checked": "2026-07-03T08:38:45.501075+00:00",
    "last_price": 457,
    "under_target": true,
    "consecutive_failures": 0,
    "failure_alert_sent": false,
    "price_log": [
      {
        "date": "2026-07-02T11:59:42.326001+00:00",
        "price": 457
      },
      {
        "date": "2026-07-02T12:07:49.908016+00:00",
        "price": 457
      },
      {
        "date": "2026-07-02T12:18:46.418401+00:00",
        "price": 457
      },
      {
        "date": "2026-07-02T12:23:16.110138+00:00",
        "price": 457
      },
      {
        "date": "2026-07-02T18:17:56.684320+00:00",
        "price": 457
      },
      {
        "date": "2026-07-03T05:07:56.422518+00:00",
        "price": 457
      },
      {
        "date": "2026-07-03T05:55:36.257252+00:00",
        "price": 457
      },
      {
        "date": "2026-07-03T05:56:39.628762+00:00",
        "price": 457
      },
      {
        "date": "2026-07-03T05:57:52.447637+00:00",
        "price": 457
      },
      {
        "date": "2026-07-03T08:38:45.501075+00:00",
        "price": 457
      }
    ]
  },
  "NYC-TYO-2026-09-24": {
    "last_checked": "2026-07-02T00:03:23.140677+00:00",
    "last_price": 1075,
    "under_target": true
  },
  "KUL-HKG-2026-07-17": {
    "last_checked": "2026-07-02T07:18:56.284266+00:00",
    "last_price": 955,
    "under_target": true
  },
  "NYC-TYO-2026-07-17": {
    "last_checked": "2026-07-02T08:10:15.222037+00:00",
    "last_price": 1189,
    "under_target": true
  },
  "NYC-TYO-2026-07-08": {
    "last_checked": "2026-07-02T07:41:15.261863+00:00",
    "last_price": 4168,
    "under_target": true
  },
  "KUL-HKG-2026-07-10": {
    "last_checked": "2026-07-02T07:54:39.852777+00:00",
    "last_price": 989,
    "under_target": true
  },
  "KUL-NYC-2026-07-17": {
    "last_checked": "2026-07-02T08:21:47.407339+00:00",
    "last_price": 932,
    "under_target": true
  },
  "KUL-BTH-2026-07-10": {
    "last_checked": "2026-07-02T10:48:26.273679+00:00",
    "last_price": 457,
    "under_target": true
  },
  "KUL-NYC-2026-07-04": {
    "last_checked": "2026-07-02T10:55:31.814665+00:00",
    "last_price": 932,
    "under_target": true
  },
  "KUL-CAN-2026-07-04": {
    "consecutive_failures": 0,
    "failure_alert_sent": false,
    "last_checked": "2026-07-02T12:18:46.418401+00:00",
    "last_price": 839,
    "under_target": true,
    "price_log": [
      {
        "date": "2026-07-02T12:07:49.908016+00:00",
        "price": 839
      },
      {
        "date": "2026-07-02T12:18:46.418401+00:00",
        "price": 839
      }
    ]
  },
  "KUL-CAN-2026-07-20": {
    "consecutive_failures": 0,
    "failure_alert_sent": false,
    "last_checked": "2026-07-02T18:17:56.684320+00:00",
    "last_price": 769,
    "under_target": true,
    "price_log": [
      {
        "date": "2026-07-02T12:23:16.110138+00:00",
        "price": 769
      },
      {
        "date": "2026-07-02T18:17:56.684320+00:00",
        "price": 769
      }
    ]
  },
  "KUL-CAN-2026-09-16": {
    "consecutive_failures": 0,
    "failure_alert_sent": false,
    "last_checked": "2026-07-03T08:38:45.501075+00:00",
    "last_price": 943,
    "under_target": true,
    "price_log": [
      {
        "date": "2026-07-03T05:07:56.422518+00:00",
        "price": 943
      },
      {
        "date": "2026-07-03T05:45:13.217820+00:00",
        "price": 943
      },
      {
        "date": "2026-07-03T05:45:48.554573+00:00",
        "price": 943
      },
      {
        "date": "2026-07-03T05:55:36.257252+00:00",
        "price": 943
      },
      {
        "date": "2026-07-03T05:56:39.628762+00:00",
        "price": 943
      },
      {
        "date": "2026-07-03T05:57:52.447637+00:00",
        "price": 943
      },
      {
        "date": "2026-07-03T08:38:45.501075+00:00",
        "price": 943
      }
    ]
  },
  "NYC-TYO-2026-07-13": {
    "consecutive_failures": 0,
    "failure_alert_sent": false,
    "last_checked": "2026-07-03T05:45:48.554573+00:00",
    "last_price": 1393,
    "under_target": true,
    "price_log": [
      {
        "date": "2026-07-03T05:45:13.217820+00:00",
        "price": 1393
      },
      {
        "date": "2026-07-03T05:45:48.554573+00:00",
        "price": 1393
      }
    ]
  },
  "KUL-TYO-2026-07-27": {
    "consecutive_failures": 0,
    "failure_alert_sent": false,
    "last_checked": "2026-07-03T08:38:45.501075+00:00",
    "last_price": 1614,
    "under_target": true,
    "price_log": [
      {
        "date": "2026-07-03T05:45:13.217820+00:00",
        "price": 1547
      },
      {
        "date": "2026-07-03T05:45:48.554573+00:00",
        "price": 1547
      },
      {
        "date": "2026-07-03T05:55:36.257252+00:00",
        "price": 1547
      },
      {
        "date": "2026-07-03T05:56:39.628762+00:00",
        "price": 1547
      },
      {
        "date": "2026-07-03T05:57:52.447637+00:00",
        "price": 1547
      },
      {
        "date": "2026-07-03T08:38:45.501075+00:00",
        "price": 1614
      }
    ]
  }
}